babpy/__init__.py
babpy/__main__.py
babpy/talk.py
babPy-0.0.5.dist-info/LICENSE
babPy-0.0.5.dist-info/METADATA
babPy-0.0.5.dist-info/WHEEL
babPy-0.0.5.dist-info/entry_points.txt
babPy-0.0.5.dist-info/top_level.txt
babPy-0.0.5.dist-info/RECORD
