Metadata-Version: 2.1
Name: babPy
Version: 0.0.5
Summary: A baby language python package
Author-email: Harry Minksy <harry.minsky@gmail.com>, Athena Leong <ayl2015@nyu.edu>, Lianna Poblete <lnp2016@nyu.edu>
License: GNU GENERAL PUBLIC LICENSE
Project-URL: Homepage, https://github.com/software-students-fall2023/3-python-package-exercise-liatha3
Project-URL: Repository, https://github.com/software-students-fall2023/3-python-package-exercise-liatha3.git
Project-URL: Bug Tracker, https://github.com/software-students-fall2023/3-python-package-exercise-liatha3/issues
Keywords: python,package,build,tutorial
Classifier: Programming Language :: Python :: 3
Classifier: Intended Audience :: Education
Classifier: License :: OSI Approved :: GNU General Public License v3 (GPLv3)
Classifier: Operating System :: OS Independent
Requires-Python: >=3.7
License-File: LICENSE
Provides-Extra: dev
Requires-Dist: pytest ; extra == 'dev'
